parapy/__init__.py
parapy-0.0.3.dist-info/LICENSE
parapy-0.0.3.dist-info/METADATA
parapy-0.0.3.dist-info/WHEEL
parapy-0.0.3.dist-info/top_level.txt
parapy-0.0.3.dist-info/RECORD
