Metadata-Version: 2.1
Name: parapy
Version: 0.0.3
Summary: An automatic handling of parameter passing to python programs.
Home-page: https://github.com/archStant/parapy
Author: Roald Simonsen
Author-email: roald.frej@hotmail.com
License: UNKNOWN
Platform: UNKNOWN
Classifier: Programming Language :: Python :: 3
Classifier: License :: OSI Approved :: GNU Lesser General Public License v3 (LGPLv3)
Classifier: Operating System :: OS Independent
